MANIFEST.in
README.rst
VERSION
setup.py
flowdas/pdk/__init__.py
flowdas/pdk/aofile.py
flowdas/pdk/app.py
flowdas/pdk/project.py
flowdas/pdk/spell.py
python_docs_ko.egg-info/PKG-INFO
python_docs_ko.egg-info/SOURCES.txt
python_docs_ko.egg-info/dependency_links.txt
python_docs_ko.egg-info/entry_points.txt
python_docs_ko.egg-info/not-zip-safe
python_docs_ko.egg-info/requires.txt
python_docs_ko.egg-info/top_level.txt