Metadata-Version: 2.1
Name: python-docs-ko
Version: 1.2.3
Summary: A toolkit for Korean translation of the Python documentation.
Home-page: https://www.flowdas.com/pages/python-docs-ko.html
Author: Flowdas Inc.
Author-email: prospero@flowdas.com
License: UNKNOWN
Project-URL: Code, https://github.com/flowdas/python-docs-ko
Project-URL: Issue tracker, https://github.com/flowdas/python-docs-ko/issues
Platform: UNKNOWN
Classifier: Development Status :: 5 - Production/Stable
Classifier: Intended Audience :: Developers
Classifier: Operating System :: OS Independent
Classifier: Programming Language :: Python
Classifier: Programming Language :: Python :: 3
Classifier: Programming Language :: Python :: 3.7
Requires-Python: >=3.7
Provides-Extra: dev
Provides-Extra: all
